mal4u/__init__.py
mal4u/api.py
mal4u/base.py
mal4u/constants.py
mal4u/details_base.py
mal4u/mixins.py
mal4u/search_base.py
mal4u/types.py
mal4u/anime/__init__.py
mal4u/anime/constants.py
mal4u/anime/mixins.py
mal4u/anime/parser.py
mal4u/anime/types.py
mal4u/characters/__init__.py
mal4u/characters/constants.py
mal4u/characters/parser.py
mal4u/characters/types.py
mal4u/manga/__init__.py
mal4u/manga/constants.py
mal4u/manga/mixins.py
mal4u/manga/parser.py
mal4u/manga/types.py
mal4u-0.2.0.dist-info/METADATA
mal4u-0.2.0.dist-info/WHEEL
mal4u-0.2.0.dist-info/top_level.txt
mal4u-0.2.0.dist-info/RECORD
