Metadata-Version: 2.1
Name: mal4u
Version: 0.2.0
Home-page: https://github.com/drhspfn/mal4u
Author: drhspfn
Author-email: jenya.gsta@gmail.com
License: MIT
Classifier: Programming Language :: Python :: 3
Classifier: License :: OSI Approved :: MIT License
Classifier: Operating System :: OS Independent
Requires-Dist: aiohttp
Requires-Dist: pydantic
Requires-Dist: beautifulsoup4
